kubric/__init__.py
kubric/logging.py
kublog-0.0.2.dist-info/LICENSE
kublog-0.0.2.dist-info/METADATA
kublog-0.0.2.dist-info/WHEEL
kublog-0.0.2.dist-info/top_level.txt
kublog-0.0.2.dist-info/RECORD
